yandex_bot/__init__.py
yandex_bot/apihelpers.py
yandex_bot/client.py
yandex_bot/handlers.py
yandex_bot/types.py
yandex_bot_py-1.0.6.dist-info/METADATA
yandex_bot_py-1.0.6.dist-info/WHEEL
yandex_bot_py-1.0.6.dist-info/licenses/LICENSE
yandex_bot_py-1.0.6.dist-info/RECORD
