Metadata-Version: 2.3
Name: yandex-bot-py
Version: 1.0.6
Summary: Python Yandex messenger bot api
Project-URL: Homepage, https://github.com/dimankaboski/yandex-bot-py
Project-URL: Repository, https://github.com/dimankaboski/yandex-bot-py
Project-URL: Issues, https://github.com/dimankaboski/yandex-bot-py/issues
Author-email: dimankaboski <dimankab@gmail.com>
License: MIT
Keywords: api,bot,messenger,tools,yandex
Classifier: Development Status :: 4 - Beta
Classifier: Environment :: Console
Classifier: License :: OSI Approved :: MIT License
Classifier: Programming Language :: Python :: 3.12
Requires-Dist: requests>=2.32.3
